kittybro_test/__init__.py
kittybro_test/kittybro_test.py
kittybro_test-0.0.2.dist-info/METADATA
kittybro_test-0.0.2.dist-info/WHEEL
kittybro_test-0.0.2.dist-info/top_level.txt
kittybro_test-0.0.2.dist-info/RECORD
