Metadata-Version: 2.1
Name: kittybro-test
Version: 0.0.2
Summary: kittybro package brings you happiness
Home-page: https://github.com/ehrlichsei/pypi_test.git
Author: kitty bro
Author-email: exmaple@gmail.com
License: UNKNOWN
Platform: UNKNOWN
Classifier: Programming Language :: Python :: 3
Classifier: License :: OSI Approved :: MIT License
Classifier: Operating System :: OS Independent
Requires-Python: >=3.6
